qa4sm_preprocessing/__init__.py
qa4sm_preprocessing/format_validator.py
qa4sm_preprocessing/ismn_grid.nc
qa4sm_preprocessing/utils.py
qa4sm_preprocessing/cgls_hr_ssm_swi/__init__.py
qa4sm_preprocessing/cgls_hr_ssm_swi/reader.py
qa4sm_preprocessing/cgls_hr_ssm_swi/reshuffle.py
qa4sm_preprocessing/cgls_hr_ssm_swi/s1cgls_nc.py
qa4sm_preprocessing/cgls_hr_ssm_swi/utils.py
qa4sm_preprocessing/ismn_frm/collect.py
qa4sm_preprocessing/level2/5deg_SMOSL2_grid.nc
qa4sm_preprocessing/level2/5deg_SMOSL2_grid_land.nc
qa4sm_preprocessing/level2/NSIDC0772_LatLon_EASE2_M36km_v1.0.nc
qa4sm_preprocessing/level2/__init__.py
qa4sm_preprocessing/level2/base.py
qa4sm_preprocessing/level2/smap.py
qa4sm_preprocessing/level2/smos.py
qa4sm_preprocessing/reading/__init__.py
qa4sm_preprocessing/reading/base.py
qa4sm_preprocessing/reading/cf.py
qa4sm_preprocessing/reading/cli.py
qa4sm_preprocessing/reading/exceptions.py
qa4sm_preprocessing/reading/image.py
qa4sm_preprocessing/reading/imagebase.py
qa4sm_preprocessing/reading/stack.py
qa4sm_preprocessing/reading/timeseries.py
qa4sm_preprocessing/reading/transpose.py
qa4sm_preprocessing/reading/utils.py
qa4sm_preprocessing/reading/write.py
qa4sm_preprocessing-0.6.1.dist-info/AUTHORS.rst
qa4sm_preprocessing-0.6.1.dist-info/LICENSE.txt
qa4sm_preprocessing-0.6.1.dist-info/METADATA
qa4sm_preprocessing-0.6.1.dist-info/WHEEL
qa4sm_preprocessing-0.6.1.dist-info/entry_points.txt
qa4sm_preprocessing-0.6.1.dist-info/top_level.txt
qa4sm_preprocessing-0.6.1.dist-info/RECORD
