Metadata-Version: 2.1
Name: qa4sm-preprocessing
Version: 0.6.1
Summary: Preprocessing routines for QA4SM
Home-page: https://github.com/pyscaffold/pyscaffold/
Author: TU Wien
Author-email: remote.sensing@geo.tuwien.ac.at
License: MIT
Project-URL: Documentation, https://pyscaffold.org/
Platform: any
Classifier: Development Status :: 4 - Beta
Classifier: Programming Language :: Python
License-File: LICENSE.txt
License-File: AUTHORS.rst
Requires-Dist: importlib-metadata
Requires-Dist: numpy
Requires-Dist: pandas
Requires-Dist: netCDF4
Requires-Dist: pyresample
Requires-Dist: pygeobase
Requires-Dist: parse
Requires-Dist: pygeogrids>=0.4.0
Requires-Dist: pynetcf
Requires-Dist: repurpose>=0.12
Requires-Dist: trollsift
Requires-Dist: xarray>=2025.01.2
Requires-Dist: zarr<=3.0.7
Requires-Dist: dask
Requires-Dist: cf-xarray
Requires-Dist: h5py
Provides-Extra: testing
Requires-Dist: setuptools; extra == "testing"
Requires-Dist: pytest; extra == "testing"
Requires-Dist: pytest-cov; extra == "testing"
